odoo/addons/l10n_ro_stock_account_notice/README.rst
odoo/addons/l10n_ro_stock_account_notice/__init__.py
odoo/addons/l10n_ro_stock_account_notice/__manifest__.py
odoo/addons/l10n_ro_stock_account_notice/i18n/l10n_ro_stock_account_notice.pot
odoo/addons/l10n_ro_stock_account_notice/i18n/ro.po
odoo/addons/l10n_ro_stock_account_notice/models/__init__.py
odoo/addons/l10n_ro_stock_account_notice/models/account_move_line.py
odoo/addons/l10n_ro_stock_account_notice/models/product.py
odoo/addons/l10n_ro_stock_account_notice/models/purchase_order.py
odoo/addons/l10n_ro_stock_account_notice/models/stock_move.py
odoo/addons/l10n_ro_stock_account_notice/models/stock_picking.py
odoo/addons/l10n_ro_stock_account_notice/readme/CONTRIBUTORS.md
odoo/addons/l10n_ro_stock_account_notice/readme/DESCRIPTION.md
odoo/addons/l10n_ro_stock_account_notice/static/description/icon.png
odoo/addons/l10n_ro_stock_account_notice/static/description/index.html
odoo/addons/l10n_ro_stock_account_notice/tests/__init__.py
odoo/addons/l10n_ro_stock_account_notice/tests/test_purchase.py
odoo/addons/l10n_ro_stock_account_notice/tests/test_retur.py
odoo/addons/l10n_ro_stock_account_notice/tests/test_sale.py
odoo/addons/l10n_ro_stock_account_notice/views/stock_picking_view.xml
odoo_addon_l10n_ro_stock_account_notice-18.0.1.6.0.1.dist-info/METADATA
odoo_addon_l10n_ro_stock_account_notice-18.0.1.6.0.1.dist-info/WHEEL
odoo_addon_l10n_ro_stock_account_notice-18.0.1.6.0.1.dist-info/top_level.txt
odoo_addon_l10n_ro_stock_account_notice-18.0.1.6.0.1.dist-info/RECORD
