Metadata-Version: 2.1
Name: odoo-addon-l10n_ro_stock_account_notice
Version: 18.0.1.6.0.1
Requires-Python: >=3.10
Requires-Dist: odoo-addon-l10n_ro_stock_account==18.0.*
Requires-Dist: odoo==18.0.*
Summary: Romania - Stock Accounting Notice
Home-page: https://github.com/OCA/l10n-romania
License: AGPL-3
Author: NextERP Romania,Dorin Hongu,Odoo Community Association (OCA)
Author-email: support@odoo-community.org
Classifier: Programming Language :: Python
Classifier: Framework :: Odoo
Classifier: Framework :: Odoo :: 18.0
Classifier: License :: OSI Approved :: GNU Affero General Public License v3
Classifier: Development Status :: 6 - Mature
